database2text/__init__.py
database2text/oracle11.py
database2text/tool.py
db2text-0.0.4.data/scripts/dbt
dbt/__init__.py
dbt/dbt.py
db2text-0.0.4.dist-info/LICENSE
db2text-0.0.4.dist-info/METADATA
db2text-0.0.4.dist-info/WHEEL
db2text-0.0.4.dist-info/top_level.txt
db2text-0.0.4.dist-info/RECORD
