Metadata-Version: 2.1
Name: db2text
Version: 0.0.4
Summary: database to text
Home-page: https://github.com/pypa/sampleproject
Author: Chen chuan
Author-email: chenc224@163.com
License: UNKNOWN
Platform: UNKNOWN
Classifier: Programming Language :: Python :: 3
Classifier: License :: OSI Approved :: MIT License
Classifier: Operating System :: OS Independent
Requires-Python: >=3.5
